cognify/__init__.py
cognify/__main__.py
cognify/_compat.py
cognify/_imports.py
cognify/_logging.py
cognify/_signal.py
cognify/_tracing.py
cognify/cognify_args.py
cognify/utils.py
cognify/frontends/__init__.py
cognify/frontends/dspy/__init__.py
cognify/frontends/dspy/connector.py
cognify/frontends/langchain/__init__.py
cognify/frontends/langchain/connector.py
cognify/graph/__init__.py
cognify/graph/base.py
cognify/graph/modules.py
cognify/graph/program.py
cognify/graph/utils.py
cognify/graph/rewriter/utils.py
cognify/hub/__init__.py
cognify/hub/cogs/__init__.py
cognify/hub/cogs/common.py
cognify/hub/cogs/decompose.py
cognify/hub/cogs/ensemble.py
cognify/hub/cogs/fewshot.py
cognify/hub/cogs/model_selection.py
cognify/hub/cogs/protection.py
cognify/hub/cogs/reasoning.py
cognify/hub/cogs/scaffolding.py
cognify/hub/cogs/utils.py
cognify/hub/cogs/decompose_agents/__init__.py
cognify/hub/cogs/decompose_agents/estimate_complexity.py
cognify/hub/cogs/decompose_agents/finalize_agents.py
cognify/hub/cogs/decompose_agents/high_level_decompose.py
cognify/hub/cogs/decompose_agents/prompts.py
cognify/hub/cogs/decompose_agents/refine_agents.py
cognify/hub/cogs/meta_programming/__init__.py
cognify/hub/cogs/meta_programming/execute_code.py
cognify/hub/cogs/meta_programming/helper.py
cognify/hub/cogs/meta_programming/mp.py
cognify/hub/cogs/tree_of_thoughts/tot.py
cognify/hub/datasets/hotpot.py
cognify/hub/evaluators/__init__.py
cognify/hub/evaluators/code_humaneval.py
cognify/hub/evaluators/f1_score.py
cognify/hub/evaluators/llm_judge.py
cognify/hub/evaluators/match.py
cognify/hub/evaluators/utils.py
cognify/hub/search/codegen.py
cognify/hub/search/datavis.py
cognify/hub/search/default.py
cognify/hub/search/qa.py
cognify/hub/search/text_to_sql.py
cognify/llm/__init__.py
cognify/llm/litellm_wrapper.py
cognify/llm/model.py
cognify/llm/output.py
cognify/llm/prompt.py
cognify/llm/response.py
cognify/optimizer/__init__.py
cognify/optimizer/control_param.py
cognify/optimizer/evaluator.py
cognify_ai-0.1.2.dist-info/LICENSE
cognify_ai-0.1.2.dist-info/METADATA
cognify_ai-0.1.2.dist-info/WHEEL
cognify_ai-0.1.2.dist-info/entry_points.txt
cognify_ai-0.1.2.dist-info/top_level.txt
cognify_ai-0.1.2.dist-info/RECORD
