Metadata-Version: 2.2
Name: cognify-ai
Version: 0.1.2
Summary: The Automated Optimizer for GenAI Workflows
Author: Cognify Team
License:                                 Apache License
Project-URL: Homepage, https://github.com/GenseeAI/cognify
Classifier: Programming Language :: Python :: 3
Classifier: License :: OSI Approved :: Apache Software License
Requires-Python: >=3.10
License-File: LICENSE
Requires-Dist: devtools
Requires-Dist: datasets
Requires-Dist: dspy-ai==2.5.32
Requires-Dist: graphviz
Requires-Dist: httpx==0.27.2
Requires-Dist: langchain==0.3.4
Requires-Dist: langchain-core==0.3.20
Requires-Dist: langchain-openai==0.2.3
Requires-Dist: litellm==1.51.0
Requires-Dist: numpy
Requires-Dist: openai==1.52.0
Requires-Dist: opentelemetry-api
Requires-Dist: opentelemetry-sdk
Requires-Dist: opentelemetry-exporter-otlp-proto-http
Requires-Dist: optuna==3.6.1
Requires-Dist: optunahub==0.1.0b0
Requires-Dist: datamodel-code-generator
Requires-Dist: astunparse
Requires-Dist: termcolor
